README.md
setup.py
Darrell.egg-info/PKG-INFO
Darrell.egg-info/SOURCES.txt
Darrell.egg-info/dependency_links.txt
Darrell.egg-info/entry_points.txt
Darrell.egg-info/requires.txt
Darrell.egg-info/top_level.txt
dar/__init__.py
dar/cli.py
dar/dbt_commands.py
dar/evidence_commands.py
dar/install.py
dar/site_commands.py
dar/utils.py
tests/__init__.py