Metadata-Version: 2.1
Name: Darrell
Version: 0.1.0
Summary: Darrell - Open Source Analytics Stack
Home-page: https://github.com/bootstrapital/darrell
Author: Chris Davis
Author-email: chris@bootstrapital.com
Classifier: Development Status :: 3 - Alpha
Classifier: Intended Audience :: Developers
Classifier: License :: OSI Approved :: MIT License
Classifier: Operating System :: OS Independent
Classifier: Programming Language :: Python :: 3
Classifier: Programming Language :: Python :: 3.9
Classifier: Programming Language :: Python :: 3.10
Classifier: Programming Language :: Python :: 3.11
Requires-Python: >=3.9
Requires-Dist: click
Requires-Dist: dbt-core
Requires-Dist: dbt-duckdb
